pygrammy/__init__.py
pygrammy/bot.py
pygrammy/composer.py
pygrammy/context.py
pygrammy/filters.py
pygrammy/input_file.py
pygrammy/keyboard.py
pygrammy/session.py
pygrammy/types.py
pygrammy-2.0.0.dist-info/METADATA
pygrammy-2.0.0.dist-info/WHEEL
pygrammy-2.0.0.dist-info/top_level.txt
pygrammy-2.0.0.dist-info/RECORD
